pyean/DejaVuSansMono.ttf
pyean/__init__.py
pyean/base.py
pyean/codex.py
pyean/ean.py
pyean/errors.py
pyean/isxn.py
pyean/itf.py
pyean/pybarcode.py
pyean/upc.py
pyean/version.py
pyean/writer.py
pyean/charsets/__init__.py
pyean/charsets/code128.py
pyean/charsets/code39.py
pyean/charsets/ean.py
pyean/charsets/itf.py
pyean/charsets/upc.py
pyean-1.1.0.dist-info/LICENCE
pyean-1.1.0.dist-info/METADATA
pyean-1.1.0.dist-info/WHEEL
pyean-1.1.0.dist-info/entry_points.txt
pyean-1.1.0.dist-info/top_level.txt
pyean-1.1.0.dist-info/RECORD
